{
  "projectName": "hp-landscaping",
  "version": "1.0.0",
  "lastUpdated": "2025-12-28T21:15:00Z",
  "currentPhase": "booking-system",
  "overallProgress": "65%",
  "deploymentURL": "TBD",
  "phases": [
    {
      "name": "foundation",
      "status": "completed",
      "progress": 100,
      "completedAt": "2025-12-27T21:00:00Z"
    },
    {
      "name": "core-features",
      "status": "completed",
      "progress": 100,
      "completedAt": "2025-12-27T23:00:00Z"
    },
    {
      "name": "booking-system",
      "status": "completed",
      "progress": 100,
      "completedAt": "2025-12-28T21:15:00Z",
      "tasks": [
        {
          "id": "booking-calendar-ui",
          "name": "Booking Calendar UI Component",
          "status": "completed",
          "agent": "Fiona-Frontend-2"
        },
        {
          "id": "booking-form",
          "name": "Appointment Booking Form",
          "status": "completed",
          "agent": "Fiona-Frontend-2"
        },
        {
          "id": "booking-page",
          "name": "Booking Page Route",
          "status": "completed",
          "agent": "Fiona-Frontend-2"
        },
        {
          "id": "booking-api",
          "name": "Booking API Endpoint",
          "status": "completed",
          "agent": "Fiona-Frontend-2"
        },
        {
          "id": "booking-integration",
          "name": "Site-wide Booking Integration",
          "status": "completed",
          "agent": "Fiona-Frontend-2"
        }
      ]
    }
  ],
  "tasks": [
    "Booking system fully implemented",
    "Calendar component with date/time selection",
    "Multi-step booking form with validation",
    "API endpoint for booking submissions",
    "Site-wide booking CTA integration"
  ],
  "availableTasks": [
    "Email notification integration for bookings",
    "Calendar system integration (Google Calendar, etc.)",
    "Database storage for bookings",
    "Admin dashboard for managing bookings",
    "SMS confirmation for appointments"
  ],
  "techStack": {
    "framework": "Next.js 16.1.1",
    "react": "React 19.2.3",
    "typescript": "TypeScript 5.x",
    "styling": "Tailwind CSS 4",
    "animation": "Framer Motion 12.23.26",
    "ui": "Radix UI Components",
    "icons": "Lucide React"
  },
  "healthStatus": {
    "build": "passing",
    "tests": "pending",
    "deployment": "pending",
    "database": "not-configured",
    "performance": "good"
  },
  "features": {
    "completed": [
      "Responsive booking calendar",
      "Multi-step appointment form",
      "Service selection interface",
      "Date and time picker",
      "Form validation",
      "Success confirmation",
      "Modal booking dialog",
      "Site-wide booking CTAs",
      "Dedicated booking page",
      "API endpoint structure"
    ],
    "inProgress": [],
    "pending": [
      "Email notifications",
      "Calendar integration",
      "Database persistence",
      "Admin dashboard",
      "SMS confirmations"
    ]
  }
}
